ovos_utils/__init__.py
ovos_utils/bracket_expansion.py
ovos_utils/decorators.py
ovos_utils/device_input.py
ovos_utils/dialog.py
ovos_utils/events.py
ovos_utils/fakebus.py
ovos_utils/file_utils.py
ovos_utils/geolocation.py
ovos_utils/gui.py
ovos_utils/json_helper.py
ovos_utils/list_utils.py
ovos_utils/log.py
ovos_utils/log_parser.py
ovos_utils/messagebus.py
ovos_utils/metrics.py
ovos_utils/network_utils.py
ovos_utils/oauth.py
ovos_utils/ocp.py
ovos_utils/parse.py
ovos_utils/process_utils.py
ovos_utils/security.py
ovos_utils/signal.py
ovos_utils/skills.py
ovos_utils/smtp_utils.py
ovos_utils/sound.py
ovos_utils/ssml.py
ovos_utils/system.py
ovos_utils/text_utils.py
ovos_utils/thread_utils.py
ovos_utils/time.py
ovos_utils/version.py
ovos_utils/xdg_utils.py
ovos_utils/xml_helper.py
ovos_utils/lang/__init__.py
ovos_utils/lang/phonemes.py
ovos_utils/lang/visimes.py
ovos_utils-0.8.4.dist-info/licenses/LICENSE
ovos_utils-0.8.4.dist-info/METADATA
ovos_utils-0.8.4.dist-info/WHEEL
ovos_utils-0.8.4.dist-info/entry_points.txt
ovos_utils-0.8.4.dist-info/top_level.txt
ovos_utils-0.8.4.dist-info/RECORD
