Metadata-Version: 2.4
Name: ovos_utils
Version: 0.8.4
Summary: collection of simple utilities for use across the openvoiceos ecosystem
Home-page: https://github.com/OpenVoiceOS/ovos_utils
Author: jarbasAI
Author-email: jarbas@openvoiceos.com
License: Apache
License-File: LICENSE
Requires-Dist: pexpect~=4.9
Requires-Dist: requests~=2.26
Requires-Dist: json_database~=0.10
Requires-Dist: kthread~=0.2
Requires-Dist: watchdog
Requires-Dist: pyee>=8.0.0
Requires-Dist: combo-lock~=0.2
Requires-Dist: rich-click~=1.7
Requires-Dist: rich~=13.7
Provides-Extra: extras
Requires-Dist: rapidfuzz<4.0,>=3.6; extra == "extras"
Requires-Dist: ovos-plugin-manager>=0.0.25; extra == "extras"
Requires-Dist: ovos-config>=0.0.12; extra == "extras"
Requires-Dist: ovos-workshop>=0.0.13; extra == "extras"
Requires-Dist: ovos_bus_client>=0.0.8; extra == "extras"
Requires-Dist: langcodes; extra == "extras"
Requires-Dist: timezonefinder; extra == "extras"
Requires-Dist: oauthlib~=3.2; extra == "extras"
Requires-Dist: orjson; extra == "extras"
Dynamic: author
Dynamic: author-email
Dynamic: description
Dynamic: description-content-type
Dynamic: home-page
Dynamic: license
Dynamic: license-file
Dynamic: provides-extra
Dynamic: requires-dist
Dynamic: summary
